SqlToDslTranslator_MCP/__init__.py
SqlToDslTranslator_MCP/__main__.py
SqlToDslTranslator_MCP/server.py
sqltodsltranslator_mcp-0.1.1.dist-info/METADATA
sqltodsltranslator_mcp-0.1.1.dist-info/WHEEL
sqltodsltranslator_mcp-0.1.1.dist-info/entry_points.txt
sqltodsltranslator_mcp-0.1.1.dist-info/RECORD
