Metadata-Version: 2.4
Name: sqltodsltranslator-mcp
Version: 0.1.1
Summary: A service to convert MySQL SQL queries to Elasticsearch DSL using MCP framework
Author-email: 'yohan' <2220041897@qq.com>
License-Expression: MIT
Requires-Python: >=3.13
Requires-Dist: build>=1.2.2.post1
Requires-Dist: fastmcp>=2.9.0
Requires-Dist: mcp[cli]>=1.9.4
Requires-Dist: twine>=6.1.0
